progress_watchdog/__init__.py
progress_watchdog/sounds/buzzer-or-wrong-answer-20582.mp3
progress_watchdog-0.1.5.dist-info/METADATA
progress_watchdog-0.1.5.dist-info/WHEEL
progress_watchdog-0.1.5.dist-info/entry_points.txt
progress_watchdog-0.1.5.dist-info/licenses/LICENSE
progress_watchdog-0.1.5.dist-info/RECORD
