Metadata-Version: 2.4
Name: progress-watchdog
Version: 0.1.5
Summary: Progress Watchdog is a Python package that helps you avoid staying stuck or getting tunnel vision while time flows by.
Author-email: Chris Patti <feoh@feoh.org>
License-Expression: MIT
License-File: LICENSE
Classifier: License :: OSI Approved :: MIT License
Classifier: Operating System :: OS Independent
Classifier: Programming Language :: Python :: 3
Requires-Python: >=3.13
Requires-Dist: playsound>=1.3.0
Requires-Dist: pynput>=1.8.0
